embrace/__init__.py
embrace/codegen.py
embrace/exceptions.py
embrace/mapobject.py
embrace/module.py
embrace/parsing.py
embrace/pool.py
embrace/poolvalidators.py
embrace/query.py
embrace/types.py
embrace/util.py
embrace-5.0.0.dist-info/licenses/LICENSE.txt
embrace-5.0.0.dist-info/METADATA
embrace-5.0.0.dist-info/WHEEL
embrace-5.0.0.dist-info/top_level.txt
embrace-5.0.0.dist-info/RECORD
