Metadata-Version: 2.4
Name: embrace
Version: 5.0.0
Summary: Embrace SQL keeps your SQL queries in SQL files. An anti-ORM inspired by HugSQL and PugSQL
Author-email: Oliver Cope <oliver@redgecko.org>
License: Apache
Project-URL: Homepage, https://sr.ht/~olly/embrace-sql
Keywords: sql,hugsql,pugsql,orm,anti-orm,files,dapper
Classifier: Development Status :: 5 - Production/Stable
Classifier: Environment :: Web Environment
Classifier: Intended Audience :: Developers
Classifier: License :: OSI Approved :: Apache Software License
Classifier: Operating System :: OS Independent
Classifier: Programming Language :: Python :: 3
License-File: LICENSE.txt
Requires-Dist: sqlparse
Requires-Dist: wrapt
Dynamic: license-file
